PyDSTool/Events.py
PyDSTool/FuncSpec.py
PyDSTool/Interval.py
PyDSTool/Model.py
PyDSTool/ModelContext.py
PyDSTool/ModelSpec.py
PyDSTool/ModelTools.py
PyDSTool/Points.py
PyDSTool/Symbolic.py
PyDSTool/Trajectory.py
PyDSTool/Variable.py
PyDSTool/__init__.py
PyDSTool/common.py
PyDSTool/conf.py
PyDSTool/errors.py
PyDSTool/integrator.py
PyDSTool/matplotlib_import.py
PyDSTool/parseUtils.py
PyDSTool/utils.py
PyDSTool/Generator/ADMC_ODEsystem.py
PyDSTool/Generator/DDEsystem.py
PyDSTool/Generator/Dopri_ODEsystem.py
PyDSTool/Generator/EmbeddedSysGen.py
PyDSTool/Generator/Euler_ODEsystem.py
PyDSTool/Generator/ExplicitFnGen.py
PyDSTool/Generator/ExtrapolateTable.py
PyDSTool/Generator/ImplicitFnGen.py
PyDSTool/Generator/InterpolateTable.py
PyDSTool/Generator/LookupTable.py
PyDSTool/Generator/MapSystem.py
PyDSTool/Generator/ODEsystem.py
PyDSTool/Generator/Radau_ODEsystem.py
PyDSTool/Generator/Vode_ODEsystem.py
PyDSTool/Generator/__init__.py
PyDSTool/Generator/allimports.py
PyDSTool/Generator/baseclasses.py
PyDSTool/Generator/messagecodes.py
PyDSTool/Generator/mixins.py
PyDSTool/PyCont/BifPoint.py
PyDSTool/PyCont/ContClass.py
PyDSTool/PyCont/Continuation.py
PyDSTool/PyCont/Makefile
PyDSTool/PyCont/Plotting.py
PyDSTool/PyCont/TestFunc.py
PyDSTool/PyCont/__init__.py
PyDSTool/PyCont/biblio_for_examples.txt
PyDSTool/PyCont/misc.py
PyDSTool/PyCont/auto/cmds/auto.env.csh
PyDSTool/PyCont/auto/cmds/auto.env.sh
PyDSTool/PyCont/auto/demos/ab/Makefile
PyDSTool/PyCont/auto/demos/ab/ab.c
PyDSTool/PyCont/auto/demos/lor/Makefile
PyDSTool/PyCont/auto/demos/lor/lor.c
PyDSTool/PyCont/auto/demos/lor/lor.c.dev
PyDSTool/PyCont/auto/demos/lor/lor.dat
PyDSTool/PyCont/auto/dev/cflow.out
PyDSTool/PyCont/auto/module/Makefile
PyDSTool/PyCont/auto/module/automod.c
PyDSTool/PyCont/auto/module/automod.i
PyDSTool/PyCont/auto/module/interface.c
PyDSTool/PyCont/auto/module/include/Makefile
PyDSTool/PyCont/auto/module/include/automod.h
PyDSTool-0.91.0.dist-info/DESCRIPTION.rst
PyDSTool-0.91.0.dist-info/METADATA
PyDSTool-0.91.0.dist-info/RECORD
PyDSTool-0.91.0.dist-info/WHEEL
PyDSTool-0.91.0.dist-info/metadata.json
PyDSTool-0.91.0.dist-info/pbr.json
PyDSTool-0.91.0.dist-info/top_level.txt
