Metadata-Version: 1.2
Name: PyDSTool
Version: 0.91.0
Summary: Python dynamical systems simulation and modeling
Home-page: https://pydstool.github.io/PyDSTool/FrontPage.html
Author: Rob Clewley; W. Erik Sherwood; M. Drew Lamar; Vladimir Zakharov
Author-email: rob.clewley@gmail.com
Maintainer: Rob Clewley
Maintainer-email: rob.clewley@gmail.com
License: BSD
Download-URL: https://github.com/robclewley/pydstool/tarball/v0.91.0
Keywords: dynamical systems,bioinformatics,modeling,bifurcation analysis
Platform: any
Classifier: Development Status :: 4 - Beta
Classifier: Topic :: Scientific/Engineering
Classifier: Intended Audience :: Science/Research
Classifier: License :: OSI Approved :: BSD License
Classifier: Programming Language :: Python :: 3.6
Classifier: Programming Language :: Python :: 3.7
Classifier: Operating System :: MacOS :: MacOS X
Classifier: Operating System :: Microsoft :: Windows
Classifier: Operating System :: POSIX :: BSD :: FreeBSD
Classifier: Operating System :: POSIX :: Linux
